pydantic_vault/__init__.py
pydantic_vault/entities.py
pydantic_vault/py.typed
pydantic_vault/vault_settings.py
pydantic_settings_vault-2.1.1.dist-info/LICENSE
pydantic_settings_vault-2.1.1.dist-info/METADATA
pydantic_settings_vault-2.1.1.dist-info/WHEEL
pydantic_settings_vault-2.1.1.dist-info/RECORD
