Metadata-Version: 2.1
Name: pydantic-settings-vault
Version: 2.1.1
Summary: A simple extension to pydantic-settings that can retrieve secrets from Hashicorp Vault
Home-page: https://github.com/aleksey925/pydantic-settings-vault/
License: MIT
Keywords: hashicorp,vault,hvac,pydantic
Author: Aleksey Petrunnik
Author-email: petrunnik.a@gmail.com
Requires-Python: >=3.8,<4.0
Classifier: Intended Audience :: Developers
Classifier: Intended Audience :: Information Technology
Classifier: Intended Audience :: System Administrators
Classifier: License :: OSI Approved :: MIT License
Classifier: Programming Language :: Python :: 3
Classifier: Programming Language :: Python :: 3.8
Classifier: Programming Language :: Python :: 3.9
Classifier: Programming Language :: Python :: 3.10
Classifier: Programming Language :: Python :: 3.11
Classifier: Programming Language :: Python :: 3.12
Classifier: Programming Language :: Python :: 3 :: Only
Classifier: Topic :: Internet
Classifier: Topic :: Security
Classifier: Topic :: Software Development
Classifier: Topic :: Software Development :: Libraries
Classifier: Topic :: Software Development :: Libraries :: Python Modules
Classifier: Typing :: Typed
Requires-Dist: hvac (>=0.10.6)
Requires-Dist: pydantic (>=2.1.1,<3)
Requires-Dist: pydantic-settings (>=2.0.2,<3)
Project-URL: Bug Tracker, https://github.com/aleksey925/pydantic-settings-vault/issues
Project-URL: Changelog, https://github.com/aleksey925/pydantic-settings-vault/blob/master/CHANGELOG.md
Project-URL: Documentation, https://github.com/aleksey925/pydantic-settings-vault/
Project-URL: Repository, https://github.com/aleksey925/pydantic-settings-vault/
